{
    "recipes": [
      {
        "id": 1,
        "name": "test",
        "ingredient1": "test",
        "amount1": "test", 
        "ingredient2": "test",
        "amount2": "test", 
        "ingredient3": "test",
        "amount3": "test", 
        "ingredient4": "test",
        "amount4": "test",
        "instructions": "test",
        "notes": "test" 
      },
      {
        "id": 2,
        "name": "test",
        "ingredient1": "test",
        "amount1": "test", 
        "ingredient2": "test",
        "amount2": "test", 
        "ingredient3": "test",
        "amount3": "test", 
        "ingredient4": "test",
        "amount4": "test",
        "instructions": "test",
        "notes": "test" 
      },
      {
        "id": 3,
        "name": "test",
        "ingredient1": "test",
        "amount1": "test", 
        "ingredient2": "test",
        "amount2": "test", 
        "ingredient3": "test",
        "amount3": "test", 
        "ingredient4": "test",
        "amount4": "test",
        "instructions": "test",
        "notes": "test" 
      },
      {
        "id": 4,
        "name": "test",
        "ingredient1": "test",
        "amount1": "test", 
        "ingredient2": "test",
        "amount2": "test", 
        "ingredient3": "test",
        "amount3": "test", 
        "ingredient4": "test",
        "amount4": "test",
        "instructions": "test",
        "notes": "test" 
      },
      {
        "id": 5,
        "name": "test",
        "ingredient1": "test",
        "amount1": "test", 
        "ingredient2": "test",
        "amount2": "test", 
        "ingredient3": "test",
        "amount3": "test", 
        "ingredient4": "test",
        "amount4": "test",
        "instructions": "test",
        "notes": "test" 
      },
      {
        "id": 6,
        "name": "test",
        "ingredient1": "test",
        "amount1": "test", 
        "ingredient2": "test",
        "amount2": "test", 
        "ingredient3": "test",
        "amount3": "test", 
        "ingredient4": "test",
        "amount4": "test",
        "instructions": "test",
        "notes": "test" 
      },
      {
        "id": 7,
        "name": "test",
        "ingredient1": "test",
        "amount1": "test", 
        "ingredient2": "test",
        "amount2": "test", 
        "ingredient3": "test",
        "amount3": "test", 
        "ingredient4": "test",
        "amount4": "test",
        "instructions": "test",
        "notes": "test" 
      }
    ]
  }